sheller.py
sheller-1.0.0.dist-info/DESCRIPTION.rst
sheller-1.0.0.dist-info/METADATA
sheller-1.0.0.dist-info/RECORD
sheller-1.0.0.dist-info/WHEEL
sheller-1.0.0.dist-info/metadata.json
sheller-1.0.0.dist-info/top_level.txt
